gerardo_burgos_pg2_tecba/__init__.py
gerardo_burgos_pg2_tecba/core.py
gerardo_burgos_pg2_tecba/validators.py
datavalidatorpy-0.0.1.dist-info/METADATA
datavalidatorpy-0.0.1.dist-info/WHEEL
datavalidatorpy-0.0.1.dist-info/top_level.txt
datavalidatorpy-0.0.1.dist-info/RECORD
